smoots/VERSION
smoots/__init__.py
smoots/log.py
smoots/py.typed
smoots/lengths/__init__.py
smoots/lengths/centimetres.py
smoots/lengths/feet.py
smoots/lengths/inches.py
smoots/lengths/length.py
smoots/lengths/metres.py
smoots/lengths/miles.py
smoots/lengths/py.typed
smoots/lengths/yards.py
smoots-1.0.0a4.dist-info/LICENSE
smoots-1.0.0a4.dist-info/METADATA
smoots-1.0.0a4.dist-info/WHEEL
smoots-1.0.0a4.dist-info/top_level.txt
smoots-1.0.0a4.dist-info/RECORD
